README.rst
setup.py
streamtest/__init__.py
streamtest/cases.py
streamtest/context.py
streamtest.egg-info/PKG-INFO
streamtest.egg-info/SOURCES.txt
streamtest.egg-info/dependency_links.txt
streamtest.egg-info/top_level.txt