Metadata-Version: 1.1
Name: streamtest
Version: 1.0b1
Summary: Python unittest.TestCase for testing the output of standard stream(stdout, stderr)
Home-page: https://github.com/alice1017/streamtest
Author: Alice1017
Author-email: takemehighermore@gmail.com
License: MIT License
Platform: UNKNOWN
Classifier: Development Status :: 4 - Beta
Classifier: Intended Audience :: Developers
Classifier: License :: OSI Approved :: MIT License
Classifier: Programming Language :: Python :: 2.7
Classifier: Topic :: Software Development :: Testing :: Unit
